deepai/__init__.py
deepai/clients/__init__.py
deepai/clients/async_client.py
deepai/clients/specialized.py
deepai/clients/sync.py
deepai/utils/__init__.py
deepai/utils/helpers.py
deepai/utils/types.py
deepai_python-0.0.1.dist-info/licenses/LICENSE
deepai_python-0.0.1.dist-info/METADATA
deepai_python-0.0.1.dist-info/WHEEL
deepai_python-0.0.1.dist-info/top_level.txt
deepai_python-0.0.1.dist-info/RECORD
